License.txt
MANIFEST.in
README
setup.py
baas/__init__.py
baas.egg-info/PKG-INFO
baas.egg-info/SOURCES.txt
baas.egg-info/dependency_links.txt
baas.egg-info/entry_points.txt
baas.egg-info/not-zip-safe
baas.egg-info/requires.txt
baas.egg-info/top_level.txt
baas/appengine/__init__.py
baas/appengine/bot_api.py
baas/appengine/bot_wave.py
baas/appengine/bot_xmpp.py
baas/conf/app.yaml
baas/conf/baas.conf
baas/core/__init__.py
baas/core/helpers.py
baas/core/plugins.py
baas/core/yqlapi.py
baas/plugins/__init__.py
baas/plugins/delicious.py
baas/plugins/example.py
baas/plugins/gsearch.py
baas/plugins/maemo.py
baas/plugins/music.py
baas/plugins/translate.py
baas/plugins/twingly.py
baas/plugins/weather.py
baas/plugins/yql.py
baas/scripts/__init__.py
baas/scripts/bot.py