Metadata-Version: 1.0
Name: baas
Version: 0.2.2
Summary: 'Buddy as a Service' is a xmpp / wavelet robot using Yahoo YQL API, Google API and other services to do searches (web, news, reviews, wikipedia, imdb) and some other stuff (translations, weather forecast, etc) for you.
Home-page: http://mborho.github.com/baas
Author: Martin Borho
Author-email: martin@borho.net
License: GNU General Public License (GPL)
Keywords: xmpp
Platform: UNKNOWN
Classifier: Programming Language :: Python :: 2.5
Classifier: Topic :: Communications :: Chat
Classifier: Development Status :: 4 - Beta
Classifier: License :: OSI Approved :: GNU General Public License (GPL)
Classifier: Intended Audience :: Other Audience
Classifier: Operating System :: POSIX :: Linux
